<annotation>
	<folder>image</folder>
	<filename>744.jpg</filename>
	<path>C:\Users\Administrator\Desktop\image\744.jpg</path>
	<source>
		<database>Unknown</database>
	</source>
	<size>
		<width>600</width>
		<height>420</height>
		<depth>3</depth>
	</size>
	<segmented>0</segmented>
	<object>
		<name>reading</name>
		<pose>Unspecified</pose>
		<truncated>0</truncated>
		<difficult>0</difficult>
		<bndbox>
			<xmin>41</xmin>
			<ymin>215</ymin>
			<xmax>106</xmax>
			<ymax>265</ymax>
		</bndbox>
	</object>
	<object>
		<name>reading</name>
		<pose>Unspecified</pose>
		<truncated>0</truncated>
		<difficult>0</difficult>
		<bndbox>
			<xmin>221</xmin>
			<ymin>229</ymin>
			<xmax>278</xmax>
			<ymax>283</ymax>
		</bndbox>
	</object>
	<object>
		<name>reading</name>
		<pose>Unspecified</pose>
		<truncated>0</truncated>
		<difficult>0</difficult>
		<bndbox>
			<xmin>340</xmin>
			<ymin>235</ymin>
			<xmax>412</xmax>
			<ymax>272</ymax>
		</bndbox>
	</object>
	<object>
		<name>reading</name>
		<pose>Unspecified</pose>
		<truncated>0</truncated>
		<difficult>0</difficult>
		<bndbox>
			<xmin>485</xmin>
			<ymin>244</ymin>
			<xmax>562</xmax>
			<ymax>295</ymax>
		</bndbox>
	</object>
</annotation>
