<annotation>
	<folder>image</folder>
	<filename>other_184.jpg</filename>
	<path>C:\Users\Administrator\Desktop\image\other_184.jpg</path>
	<source>
		<database>Unknown</database>
	</source>
	<size>
		<width>589</width>
		<height>800</height>
		<depth>3</depth>
	</size>
	<segmented>0</segmented>
	<object>
		<name>no-phone</name>
		<pose>Unspecified</pose>
		<truncated>0</truncated>
		<difficult>0</difficult>
		<bndbox>
			<xmin>337</xmin>
			<ymin>381</ymin>
			<xmax>425</xmax>
			<ymax>513</ymax>
		</bndbox>
	</object>
	<object>
		<name>no-phone</name>
		<pose>Unspecified</pose>
		<truncated>0</truncated>
		<difficult>0</difficult>
		<bndbox>
			<xmin>87</xmin>
			<ymin>350</ymin>
			<xmax>164</xmax>
			<ymax>464</ymax>
		</bndbox>
	</object>
</annotation>